src/__init__.py
src/main.py
src/version.py
src/client/__init__.py
src/client/client.py
src/client/exceptions.py
src/client/generated/README.md
src/client/generated/__init__.py
src/client/generated/api_client.py
src/client/generated/api_response.py
src/client/generated/configuration.py
src/client/generated/exceptions.py
src/client/generated/rest.py
src/client/generated/api/__init__.py
src/client/generated/api/custom_field_controller_api.py
src/client/generated/api/custom_field_project_controller_api.py
src/client/generated/api/custom_field_project_controller_v2_api.py
src/client/generated/api/custom_field_schema_controller_api.py
src/client/generated/api/custom_field_value_controller_api.py
src/client/generated/api/custom_field_value_project_controller_api.py
src/client/generated/api/launch_controller_api.py
src/client/generated/api/launch_search_controller_api.py
src/client/generated/api/project_controller_api.py
src/client/generated/api/shared_step_attachment_controller_api.py
src/client/generated/api/shared_step_controller_api.py
src/client/generated/api/shared_step_scenario_controller_api.py
src/client/generated/api/status_controller_api.py
src/client/generated/api/test_case_attachment_controller_api.py
src/client/generated/api/test_case_bulk_controller_api.py
src/client/generated/api/test_case_controller_api.py
src/client/generated/api/test_case_custom_field_controller_api.py
src/client/generated/api/test_case_overview_controller_api.py
src/client/generated/api/test_case_scenario_controller_api.py
src/client/generated/api/test_case_search_controller_api.py
src/client/generated/api/test_case_tag_controller_api.py
src/client/generated/docs/AccessGroupBulkDto.md
src/client/generated/docs/AccessGroupCreateDto.md
src/client/generated/docs/AccessGroupDto.md
src/client/generated/docs/AccessGroupPaDto.md
src/client/generated/docs/AccessGroupPatchDto.md
src/client/generated/docs/AccessGroupProjectAccessDto.md
src/client/generated/docs/AccessGroupProjectsAddDto.md
lucius_mcp-0.2.2.dist-info/METADATA
lucius_mcp-0.2.2.dist-info/WHEEL
lucius_mcp-0.2.2.dist-info/entry_points.txt
lucius_mcp-0.2.2.dist-info/licenses/LICENSE
lucius_mcp-0.2.2.dist-info/RECORD
