Metadata-Version: 2.4
Name: lucius-mcp
Version: 0.2.2
Summary: Allure TestOps MCP Server
Project-URL: Homepage, https://github.com/ivanostanin/lucius-mcp
Project-URL: Documentation, https://github.com/ivanostanin/lucius-mcp#readme
Project-URL: Repository, https://github.com/ivanostanin/lucius-mcp.git
Project-URL: Issues, https://github.com/ivanostanin/lucius-mcp/issues
Project-URL: Changelog, https://github.com/ivanostanin/lucius-mcp/blob/main/CHANGELOG.md
Project-URL: Releases, https://github.com/ivanostanin/lucius-mcp/releases
Author-email: Ivan Ostanin <ivan@ostanin.me>
License-Expression: Apache-2.0
License-File: LICENSE
Keywords: allure,allure-testops,fastmcp,mcp,mcp-server,model-context-protocol,testops
Classifier: Development Status :: 4 - Beta
Classifier: Environment :: Console
Classifier: Intended Audience :: Developers
Classifier: Natural Language :: English
Classifier: Operating System :: OS Independent
Classifier: Programming Language :: Python :: 3
Classifier: Programming Language :: Python :: 3.14
Classifier: Topic :: Software Development
Classifier: Topic :: Software Development :: Quality Assurance
Classifier: Topic :: Software Development :: Testing
Classifier: Topic :: Utilities
Classifier: Typing :: Typed
Requires-Python: >=3.14
Requires-Dist: fastmcp>=2.14.4
Requires-Dist: httpx>=0.28.1
Requires-Dist: pydantic-settings>=2.12.0
Requires-Dist: pydantic>=2.12.5
Requires-Dist: python-dateutil>=2.9.0.post0
Requires-Dist: python-json-logger>=2.0.7
Requires-Dist: rich>=13.7.0
Requires-Dist: starlette==0.52.1
Requires-Dist: uvicorn>=0.40.0
Requires-Dist: wsproto>=1.3.2
Provides-Extra: dev
Requires-Dist: allure-pytest>=2.15.3; extra == 'dev'
Requires-Dist: faker>=40.1.2; extra == 'dev'
Requires-Dist: mypy>=1.19.1; extra == 'dev'
Requires-Dist: openapi-generator-cli>=7.19.0; extra == 'dev'
Requires-Dist: pre-commit>=4.0.0; extra == 'dev'
Requires-Dist: pytest-asyncio>=1.3.0; extra == 'dev'
Requires-Dist: pytest-cov>=7.0.0; extra == 'dev'
Requires-Dist: pytest-mock>=3.15.1; extra == 'dev'
Requires-Dist: pytest>=9.0.2; extra == 'dev'
Requires-Dist: respx>=0.22.0; extra == 'dev'
Requires-Dist: ruff>=0.14.14; extra == 'dev'
Requires-Dist: twine>=6.2.0; extra == 'dev'
